coco_pano_ext_demo/__init__.py
coco_pano_ext_demo/coco.py
coco_pano_ext_demo/iou.py
coco_pano_ext_demo/prec_recall_map.py
coco_pano_ext_demo-0.0.1.dist-info/LICENSE
coco_pano_ext_demo-0.0.1.dist-info/METADATA
coco_pano_ext_demo-0.0.1.dist-info/WHEEL
coco_pano_ext_demo-0.0.1.dist-info/top_level.txt
coco_pano_ext_demo-0.0.1.dist-info/RECORD
